pandas_xlwt/__init__.py
pandas_xlwt/_xlwt.py
pandas_xlwt-0.1.1.dist-info/LICENSE
pandas_xlwt-0.1.1.dist-info/METADATA
pandas_xlwt-0.1.1.dist-info/WHEEL
pandas_xlwt-0.1.1.dist-info/RECORD
