Metadata-Version: 2.1
Name: pandas-xlwt
Version: 0.1.1
Summary: 
Author: Yibo Mao
Author-email: maoyibo@gmail.com
Requires-Python: >=3.8,<4.0
Classifier: Programming Language :: Python :: 3
Classifier: Programming Language :: Python :: 3.8
Classifier: Programming Language :: Python :: 3.9
Classifier: Programming Language :: Python :: 3.10
Classifier: Programming Language :: Python :: 3.11
Requires-Dist: pandas (>=2.0.0,<2.1.0)
Requires-Dist: xlwt (>=1.3.0,<2.0.0)
